pandas_gdc_agent/__init__.py
pandas_gdc_agent/capabilities.json
pandas_gdc_agent/gdc_agent_utils.py
pandas_gdc_agent/pandas_gdc_agent.py
pandas_gdc_agent-0.0.3.dist-info/METADATA
pandas_gdc_agent-0.0.3.dist-info/WHEEL
pandas_gdc_agent-0.0.3.dist-info/licenses/LICENSE
pandas_gdc_agent-0.0.3.dist-info/RECORD
