Metadata-Version: 2.1
Name: pandas_gdc_agent
Version: 0.0.3
Summary: Hasura GDC agent based on pandas.
Project-URL: Homepage, https://github.com/paritosh-08/pandas_gdc_agent
Project-URL: Bug Tracker, https://github.com/paritosh-08/pandas_gdc_agent/issues
Author-email: Paritosh Raj <paritosh@hasura.io>
License: MIT License
Classifier: License :: OSI Approved :: MIT License
Classifier: Operating System :: OS Independent
Classifier: Programming Language :: Python :: 3
Requires-Python: >=3.8
Requires-Dist: flask==2.1.2
Requires-Dist: pandas==1.4.3
